gee_fwi/FWI.py
gee_fwi/FWIInputs.py
gee_fwi/__init__.py
gee_fwi-1.0.1.dist-info/LICENSE
gee_fwi-1.0.1.dist-info/METADATA
gee_fwi-1.0.1.dist-info/WHEEL
gee_fwi-1.0.1.dist-info/top_level.txt
gee_fwi-1.0.1.dist-info/RECORD
